binspec/__init__.py
binspec/errors.py
binspec/spec.py
binspec/types/__init__.py
binspec/types/spec_type.py
binspec/ui/__init__.py
binspec/ui/ui.py
binspec/utilities/__init__.py
binspec/utilities/utilities.py
binspec-1.0.0.dist-info/LICENSE
binspec-1.0.0.dist-info/METADATA
binspec-1.0.0.dist-info/WHEEL
binspec-1.0.0.dist-info/top_level.txt
binspec-1.0.0.dist-info/RECORD
