Metadata-Version: 2.1
Name: binspec
Version: 1.0.0
Summary: BinSpec (short for Binary Specification) is a binary parsing library built with Python 3.
Author: zeplar exe
Project-URL: Homepage, https://github.com/zeplar-exe/BinSpec.py
Project-URL: Issues, https://github.com/zeplar-exe/BinSpec.py/issues
Classifier: Programming Language :: Python :: 3
Classifier: License :: OSI Approved :: MIT License
Classifier: Operating System :: OS Independent
Requires-Python: >=3.8
License-File: LICENSE
